llm_grok.py
llm_grok-1.3.0.dist-info/licenses/LICENSE
llm_grok-1.3.0.dist-info/METADATA
llm_grok-1.3.0.dist-info/WHEEL
llm_grok-1.3.0.dist-info/entry_points.txt
llm_grok-1.3.0.dist-info/top_level.txt
llm_grok-1.3.0.dist-info/RECORD
