Metadata-Version: 2.4
Name: llm-grok
Version: 1.3.0
Summary: LLM plugin providing access to Grok models using the xAI API
Author: Benedikt Hiepler
License-Expression: Apache-2.0
Project-URL: Homepage, https://github.com/hiepler/llm-grok
Project-URL: Changelog, https://github.com/hiepler/llm-grok/releases
Project-URL: Issues, https://github.com/hiepler/llm-grok/issues
Project-URL: CI, https://github.com/hiepler/llm-grok/actions
License-File: LICENSE
Requires-Dist: llm>=0.17
Requires-Dist: httpx
Requires-Dist: httpx-sse
Requires-Dist: rich>=10.0.0
Provides-Extra: test
Requires-Dist: pytest; extra == "test"
Requires-Dist: pytest-httpx; extra == "test"
Dynamic: license-file
